notebooks/__init__.py
tests/__init__.py
tests/test_textsplit.py
textsplit/__init__.py
textsplit/algorithm.py
textsplit/tools.py
textsplit-0.5.dist-info/LICENSE
textsplit-0.5.dist-info/METADATA
textsplit-0.5.dist-info/WHEEL
textsplit-0.5.dist-info/top_level.txt
textsplit-0.5.dist-info/RECORD
