Metadata-Version: 2.1
Name: textsplit
Version: 0.5
Summary: Segment documents into coherent parts using wordembeddings.
Home-page: https://github.com/chschock/textsplit
Author: Christoph Schock
Author-email: chschock@gmail.com
License: MIT
Keywords: nlp text segmentation paragraph embeddings
Platform: UNKNOWN
Classifier: Programming Language :: Python :: 3.6
Classifier: License :: OSI Approved :: MIT License
Classifier: Operating System :: OS Independent
Classifier: Topic :: Scientific/Engineering :: Artificial Intelligence
Requires-Dist: nose (>=1.3.7)
Requires-Dist: numpy (>=1.13.1)
